pytest_result_sender_jms-0.1.6.dist-info/METADATA
pytest_result_sender_jms-0.1.6.dist-info/WHEEL
pytest_result_sender_jms-0.1.6.dist-info/entry_points.txt
pytest_result_sender_jms/__init__.py
pytest_result_sender_jms/plugin.py
pytest_result_sender_jms-0.1.6.dist-info/RECORD
