Metadata-Version: 2.1
Name: pytest-result-sender-jms
Version: 0.1.6
Summary: Default template for PDM package
Author-Email: Your Name <your.email@example.com>
License: MIT
Requires-Python: >=3.8
Requires-Dist: pytest>=8.3.5
Requires-Dist: requests>=2.32.3
Requires-Dist: charset-normalizer>=3.4.2
Requires-Dist: black>=24.8.0
